<?xml version="1.0" encoding="ISO-8859-1" ?><?xml-stylesheet type="text/xsl" href="../folio.xsl" ?><folio tale="fr" n="82" side="r" label="82r" order="2" total="9">
<l frag="III" benson="1331" n="31">Ne neuäe shuln , terme of al here lyues</l>
<l frag="III" benson="1332" n="32">Peter so ben the wo~men , of the styues</l>
<l frag="III" benson="1333" n="33">Quod the Sompnour , I put out of oure cure</l>
<l frag="III" benson="1334" n="34">Pees w  myschaunce , and witú mysauenture</l>
<l frag="III" benson="1335" n="35">Thus seide oure host , and late hi~ telle his tale</l>
<l frag="III" benson="1336" n="36">Now telleth fortú , and lat the Sompnour gale</l>
<l frag="III" benson="1337" n="37">Ne sparetú nougút , myn owen maister deere</l>
<l frag="III" benson="1338" n="38">This fals thef , this Sompnour , q¶ the frere</l>
<l frag="III" benson="1339" n="39">Had alwey , Baudes , redy to his hond</l>
<l frag="III" benson="1340" n="40">As ony hauke , to lure in Engelond</l>
<l frag="III" benson="1341" n="41">That told hi~ al the secree , that they knewe</l>
<l frag="III" benson="1342" n="42">For hire acqueyntaunce , was nat comen of newe</l>
<l frag="III" benson="1343" n="43">They weren hise approwoures , preuyly</l>
<l frag="III" benson="1344" n="44">He tok hi~ self , a gret profyt ther by</l>
<l frag="III" benson="1345" n="45">His maister knew nat alwey , what he wan</l>
<l frag="III" benson="1346" n="46">Witú outen maundement , a lewed man</l>
<l frag="III" benson="1347" n="47">He coude sompne , vp peyne of cristes curs</l>
<l frag="III" benson="1348" n="48">And they were Inly glad , for to fille his purs</l>
<l frag="III" benson="1349" n="49"><emph>A</emph>nd make hi~ greete festis , at the nale</l>
<l frag="III" benson="1350" n="50">And rigút as Iudas , had purses smale</l>
<l frag="III" benson="1351" n="51">And was a thef , rigút swicú a thef was he</l>
<l frag="III" benson="1352" n="52">His maister had but half , his duete</l>
<l frag="III" benson="1353" n="53">He was , if I shal ©euen <app><orig><absent>&#32;</absent></orig><c1>hi~</c1><lit><i>hi~</i></lit></app> his<app><orig>lande</orig><c1>lavde</c1><lit>la<rp><cow>n</cow>v</rp>de~</lit></app> <note><notetxt><q>lavde</q><ctp>53</ctp> The v of this word appears to be a combination of v and u or an n. Also double check the interlinear correction in the former word.<resp>Est/ODR</resp></notetxt></note></l>
<l frag="III" benson="1354" n="54">A thef , and eke a Sompnour , and a baude</l>
<l frag="III" benson="1355" n="55">He had eke wenchis , at his retynew</l>
<l frag="III" benson="1356" n="56">That wheither Sire Robert , or Sire Heugúe</l>
<l frag="III" benson="1357" n="57">Or Ioún or Raf , or who so that it were</l>
<l frag="III" benson="1358" n="58">That lay by hem , they told it in his eere</l>
<l frag="III" benson="1359" n="59">Thus was the wenche , and he of oon assent</l>
<l frag="III" benson="1360" n="60">And he wold fecche , a feyned maundement</l>
<l frag="III" benson="1361" n="61">And sompne hem to chapetle , bothe two</l>
<l frag="III" benson="1362" n="62">And pille the man , and late the wenche go</l>
<l frag="III" benson="1363" n="63">Than wold he sey frend , I shal for thy sake</l>
<l frag="III" benson="1364" n="64">Do strike the out , of oure &#38;lbar;res blake</l>
<l frag="III" benson="1365" n="65">The thar nomore , as in this cas trauaille</l>
<l frag="III" benson="1366" n="66">I am thy frend , there I may the auaille</l>
<l frag="III" benson="1367" n="67">Certeyn he knew , of bryboures moo</l>
<l frag="III" benson="1368" n="68">Than possible is , to telle in ©eres twoo</l>
<l frag="III" benson="1369" n="69">For in this world , nys dogge for the bowe</l>
<l frag="III" benson="1370" n="70">That can an hurt Deer , from an hol bet knowe</l>
<l frag="III" benson="1371" n="71">Than that this Sompnour , knew a sly lechour</l>
<l frag="III" benson="1372" n="72">Or on aduouter , or a Paramour</l>
<l frag="III" benson="1373" n="73">And for that was the fruyt , of al his rente</l>
<l frag="III" benson="1374" n="74">Therfore on it he sette , al his entente</l>
<l frag="III" benson="1375" n="75">And so byfel , that ones vp on a day</l>
<l frag="III" benson="1376" n="76">This sompnour euäe , waytyngö on his pray</l></folio>
