<?xml version="1.0" encoding="ISO-8859-1" ?>
<?xml-stylesheet type="text/xsl" href="../folio.xsl" ?>
<folio tale="kn" n="36" side="v" label="36v" order="32" total="35">
<l frag="I" benson="2882" n="2018">¢ Tho cam this wooful Theaban , Palamou~</l>
<l frag="I" benson="2883" n="2019">With flotry berd , and ruggy asshy heres</l>
<l frag="I" benson="2884" n="2020">In clothes blake , I dropped al with teres</l>
<l frag="I" benson="2885" n="2021">And passyng othere , of wepyng , Emelye</l>
<l frag="I" benson="2886" n="2022">The reufullest , of al the companye</l>
<l frag="I" benson="2887" n="2023">And in as meche , as the seruyse shuld be</l>
<l frag="I" benson="2888" n="2024">The more noble , and riche in his degree</l>
<l frag="I" benson="2889" n="2025"><emph>D</emph>uke Theseus , let forth the steedes bryng</l>
<l frag="I" benson="2890" n="2026">That trapped weren , in stele al glet äyng</l>
<l frag="I" benson="2891" n="2027">And couäed with the Armes , of daun Arcite</l>
<l frag="I" benson="2892" n="2028">Vp on the steedes , grete and whyte</l>
<l frag="I" benson="2893" n="2029">There seten folk , of which on bar his shelde</l>
<l frag="I" benson="2894" n="2030">A nother his spere , vp on his hondes helde</l>
<l frag="I" benson="2895" n="2031">They bar with hi~ , his bowe Turkeys</l>
<l frag="I" benson="2896" n="2032">Of brend gold was the caas , &#38; eke the harneys</l>
<l frag="I" benson="2897" n="2033">And riden forth a paas , with sorweful chere</l>
<l frag="I" benson="2898" n="2034">Toward the Groue , as ©e shuln after here</l>
<l frag="I" benson="2899" n="2035">The noblest of the Grekys , that there were</l>
<l frag="I" benson="2900" n="2036">Vp on here shuldres , carieden the bere</l>
<l frag="I" benson="2901" n="2037">With slakke paas , and eyen rede and wete</l>
<l frag="I" benson="2902" n="2038">Thorugú ou©t the Citee , by the maister strete</l>
<l frag="I" benson="2903" n="2039">That spred was al with blak , and wonder hye</l>
<l frag="I" benson="2904" n="2040">Rygút of the same , is the strete I wrye</l>
<l frag="I" benson="2905" n="2041">¢ Vp on the rigút hand , went old Egeus</l>
<l frag="I" benson="2906" n="2042">And on that other side , Duke Theseus</l>
<l frag="I" benson="2907" n="2043">With vesseles in here handes , of gold ful fyne</l>
<l frag="I" benson="2908" n="2044"><emph>A</emph>l ful of hony , melk , Blod , and wyne</l>
<l frag="I" benson="2909" n="2045">Eke Palamou~ , with ful gret companye</l>
<l frag="I" benson="2910" n="2046">And after <app><orig><absent>&#32;</absent></orig><c1>æ </c1><lit><i>æ </i></lit></app> cam , wooful Emelye</l>
<l frag="I" benson="2911" n="2047">Witú fir in hand , as was æ  tyme the gyse</l>
<l frag="I" benson="2912" n="2048">To do the offise , of FuneraÂ seruyce</l>
<l frag="I" benson="2913" n="2049">¢ Heigú labour , and gret apparaillyng</l>
<l frag="I" benson="2914" n="2050">Was at the seruice , and the fir makyng</l>
<l frag="I" benson="2915" n="2051">That with his grene top , the heuene laugút</l>
<l frag="I" benson="2916" n="2052">And xx é , fadome of brede , the armes straugút</l>
<l frag="I" benson="2917" n="2053">This is to seyn , the bowes were so brode</l>
<l frag="I" benson="2918" n="2054">Of stree first , there was leid many a lode</l>
<l frag="I" benson="2919" n="2055">¢ But how the fire , was maked vp on heigút</l>
<l frag="I" benson="2920" n="2056">Ne eke the names , how the trees higút</l>
<l frag="I" benson="2921" n="2057">As Oke fir , Birche , Aspe , Alder , holm , Popler</l>
<l frag="I" benson="2922" n="2058">Wylew , Elmö , Plane , Assú , Box , Chesteyn , lynde , laurer</l>
<l frag="I" benson="2923" n="2059">Mapul , Thorn~ , Beche , hasel , Ew , whippeltre</l>
<l frag="I" benson="2924" n="2060">How they were feld , shal nat be told for me</l>
<l frag="I" benson="2925" n="2061">¢ Ne how the goddes , ronnen vp and doun</l>
<l frag="I" benson="2926" n="2062"><emph>D</emph>isherited , of here habitaciou~ ,</l><note><notetxt><ctp>2062</ctp>missing f.37.<resp>ODR</resp></notetxt></note>
</folio>
