<?xml version="1.0" encoding="ISO-8859-1" ?>
<?xml-stylesheet type="text/xsl" href="../folio.xsl" ?>
<folio tale="kn" n="19" side="v" label="19v" order="8" total="35">
<l frag="I" benson="1375" n="517">Engendred , of humoå , malicolyk´</l>
<l frag="I" benson="1376" n="518">Byforn his owenö , Celle fantasyk´</l><note><notetxt><ctp>518</ctp>There is a cross in dry point in the left margin.<resp>ODR</resp></notetxt></note>
<l frag="I" benson="1377" n="519">And shortly tåned , was al vp so doun</l>
<l frag="I" benson="1378" n="520">Bothe habit , and eke disposiciou~</l>
<l frag="I" benson="1379" n="521">Of hym , this wooful louyer Arcite</l>
<l frag="I" benson="1380" n="522">What shuld I al day , of hys woo endite</l>
<l frag="I" benson="1381" n="523">Whan he endured had , a ©ere or two</l>
<l frag="I" benson="1382" n="524">Thys cruel tåment , &#38; this peyne &#38; woo</l>
<l frag="I" benson="1383" n="525">At Thebes in his contre , as I seyde</l>
<l frag="I" benson="1384" n="526">Vp on a nygút in slepe , as he hi~ leyde</l>
<l frag="I" benson="1385" n="527">Hi~ æou©t how æ  , the wynged god M äcurie</l>
<l frag="I" benson="1386" n="528">Byforn hi~ stod , &#38; bad hi~ to be merie</l>
<l frag="I" benson="1387" n="529">His slepy yerde , in honde he bar vp rigút</l>
<l frag="I" benson="1388" n="530">An hatte he wered , vp on his heris brigút</l>
<l frag="I" benson="1389" n="531">Arrayed was æis god , as I tok kepe</l>
<l frag="I" benson="1390" n="532">As he was , whan Argus , toke his slepe</l>
<l frag="I" benson="1391" n="533">And seide hi~ thus , to Athenes shalt æè wende</l>
<l frag="I" benson="1392" n="534">There is the shapen , of thy woo an ende</l>
<l frag="I" benson="1393" n="535">¢ <emph>A</emph>nd with that word , Arcite woke and stirt´</l>
<l frag="I" benson="1394" n="536">Now trewely , how sore æat me smert</l>
<l frag="I" benson="1395" n="537">Quod he , to Athenes , rigút now wyl I fare</l>
<l frag="I" benson="1396" n="538">Ne for the drede of deth , I wyl nat spare</l>
<l frag="I" benson="1397" n="539">To se my lady , whom æat I loue and serue</l><note><notetxt><q>serue</q><ctp>539</ctp> s has a double assender.<resp>ODR</resp></notetxt></note>
<l frag="I" benson="1398" n="540">In hire päsence , I rekke nou©t , thougú I sterue</l>
<l frag="I" benson="1399" n="541">And w  æat word , he caugút a gret Myrour</l>
<l frag="I" benson="1400" n="542">And saw , æ  chaunged was , al his colour</l>
<l frag="I" benson="1401" n="543">And saw his visage , al in an oæer kynde</l>
<l frag="I" benson="1402" n="544">And rigút a non , it ran hi~ in his mynde</l>
<l frag="I" benson="1403" n="545">That sithe his face , was so disfigure¶</l>
<l frag="I" benson="1404" n="546">Of maladye , that he had endure¶</l>
<l frag="I" benson="1405" n="547">He mygút wele ©eue , that he bare hym lowe</l>
<l frag="I" benson="1406" n="548">Lyue in Athenes , euäemore vnknowe</l>
<l frag="I" benson="1407" n="549">And sen his lady , wel ny day by day</l>
<l frag="I" benson="1408" n="550">And rigút a non , he chaunged his array</l>
<l frag="I" benson="1409" n="551">And clad hi~ , as a pore laborere</l>
<l frag="I" benson="1410" n="552">And al a lone , saue oonly a Squyere</l><note><notetxt><q>Squyere</q><ctp>552</ctp>q is left open in the head.There is a thin stroke across.<resp>ODR</resp></notetxt></note>
<l frag="I" benson="1411" n="553">That knew his preuyte , and al his cas</l>
<l frag="I" benson="1412" n="554">Whicú was disgysed , porely as he was</l>
<l frag="I" benson="1413" n="555">To a Athenes is he gon , the next wey</l>
<l frag="I" benson="1414" n="556">And to the court , he com on a dey</l>
<l frag="I" benson="1415" n="557">And at the gate , he profred his seruyse</l><note><notetxt><q>seruyse</q><ctp>557</ctp>s has a double stem.<resp>ODR</resp></notetxt></note>
</folio>
