<?xml version="1.0" encoding="ISO-8859-1" ?><?xml-stylesheet type="text/xsl" href="../folio.xsl" ?><folio tale="wbp" n="73" side="r" label="73r" order="13" total="20">
<l frag="III" benson="511" n="511">That thougú he had , me bete on euäy bon</l>
<l frag="III" benson="512" n="512">He coude wynne , my loue a geyn a noon</l>
<l frag="III" benson="513" n="513">I trowe I loued hi~ best , for that he</l>
<l frag="III" benson="514" n="514">Was of his loue , daungerous vn to me</l>
<l frag="III" benson="515" n="515">We wommen han , if that I shal nat lye</l>
<l frag="III" benson="516" n="516">In this mater , a queynt fantasie</l>
<l frag="III" benson="517" n="517">Wayte what thyngö , we may nat ligútly haue</l>
<l frag="III" benson="518" n="518">Ther after wyl we crye alday , and craue</l>
<l frag="III" benson="519" n="519">¢ Forbede vs thyngö , and that desiren we</l>
<l frag="III" benson="520" n="520">Presse on vs fast , and than wol we flee</l>
<l frag="III" benson="521" n="521">Witú daunger outer we , al oure chaffare</l>
<l frag="III" benson="522" n="522">Greet prees at market , maketú dere ware</l>
<l frag="III" benson="523" n="523">And to gret chep~ , is holden at litel pris</l>
<l frag="III" benson="524" n="524">This knowetú euäy wo~man , that is wys</l>
<l frag="III" benson="525" n="525">¢ My ferthe husbonde , god his soule blisse</l>
<l frag="III" benson="526" n="526">Whicú that I took , for loue &#38; no richesse</l>
<l frag="III" benson="527" n="527">He somtyme was , a Clerk of Oxenforde</l>
<l frag="III" benson="528" n="528">And had left scole , and went at hom to borde</l>
<l frag="III" benson="529" n="529">Witú my gossyp~ , dwellynge in oure tounö</l>
<l frag="III" benson="530" n="530">God haue hire soule , hire name was Alisouö</l>
<l frag="III" benson="531" n="531">She knew myn hert , and al my preuytee</l>
<l frag="III" benson="532" n="532">Bet than oure parissú preest , so mot I the</l>
<l frag="III" benson="533" n="533">To hire be wreyed I , my counseil al</l>
<l frag="III" benson="534" n="534">For had myn husbonde , pissed on a wal</l>
<l frag="III" benson="535" n="535">Or don a thyngö , that shuld han cost his lif</l>
<l frag="III" benson="536" n="536">To hire , and to a nother worthy wyf</l>
<l frag="III" benson="537" n="537"><emph>A</emph>nd to my Nece , whiche that I loued wel</l>
<l frag="III" benson="538" n="538">I wold han told , his counseil euäydel</l>
<l frag="III" benson="539" n="539">And so I dide ful often , god it woot</l>
<l frag="III" benson="540" n="540">That mad his face , ful often red and hoot´</l>
<l frag="III" benson="541" n="541">ffor verray shame , and blamed hi~ self for he</l>
<l frag="III" benson="542" n="542">Had told to me , so gret a preuytee</l>
<l frag="III" benson="543" n="543">And so byfel , that ones in a lente</l>
<l frag="III" benson="544" n="544">So often tymes , I to my gossip~ wente</l>
<l frag="III" benson="545" n="545">For euäe ©et , I loued to be gay</l>
<l frag="III" benson="546" n="546"><emph>A</emph>nd for to walke , in Marcú ApriÂ &#38; May</l>
<l frag="III" benson="547" n="547">ffro hous to hous , to here sondry tales</l>
<l frag="III" benson="548" n="548">That Iankyn Clerk , &#38; my gossip~ Dame Ales</l>
<l frag="III" benson="549" n="549">And I my selue , in to the feeldes went</l>
<l frag="III" benson="550" n="550">Myn husbonde was at londou~ , al that lent</l>
<l frag="III" benson="551" n="551">I had the betir leiser , for to pleye</l>
<l frag="III" benson="552" n="552">And for to se , and eke for to be seye</l>
<l frag="III" benson="553" n="553">Of lusty folk , what wyst I , where my grace</l>
<l frag="III" benson="554" n="554">Was shapen for to be , or in what place</l></folio>
