<?xml version="1.0" encoding="ISO-8859-1" ?><?xml-stylesheet type="text/xsl" href="../folio.xsl" ?><folio tale="wbp" n="69" side="v" label="69v" order="6" total="20">
<l frag="III" benson="201" n="201"><emph>A</emph>s god helpe me , I laugúe whan that I thynke</l><note><notetxt><ctp>201</ctp>There is a cross in the top left margin next to the firt line.<resp>ODR</resp></notetxt></note>
<l frag="III" benson="202" n="202">How pitously a nygút , I made hem swynke</l>
<l frag="III" benson="203" n="203">But be me fey , I tolde of it no store</l>
<l frag="III" benson="204" n="204">They had me ©euen , here lond and here tresore</l>
<l frag="III" benson="205" n="205">Me neded nat , do lengere diligence</l>
<l frag="III" benson="206" n="206">To wynne here loue , or do hem reuerence</l>
<l frag="III" benson="207" n="207">They loued me so wel , by god a boue</l>
<l frag="III" benson="208" n="208">That I ne told , no deynte of here loue</l>
<l frag="III" benson="209" n="209">A wys wo~man , wyl besy hire euäe in oon</l>
<l frag="III" benson="210" n="210">To geten hire loue , there as she hatú noon</l>
<l frag="III" benson="211" n="211">But syn I had hem , holly in myn hand</l>
<l frag="III" benson="212" n="212"><emph>A</emph>nd syn that they , had ©eue me al here land</l><note><notetxt><ctp>213</ctp>Cross in dry point in the left margin.<resp>ODR</resp></notetxt></note>
<l frag="III" benson="213" n="213">What shulde I take kepe , hem for to pleese</l>
<l frag="III" benson="214" n="214">But if it were for my ¸fyt , and myn eese</l>
<l frag="III" benson="215" n="215">I sette hem so a werk , be my fey</l>
<l frag="III" benson="216" n="216">That many a nygút , they songen weylawey</l>
<l frag="III" benson="217" n="217">The baconö was nat fet , for hem as I trowe</l>
<l frag="III" benson="218" n="218">That su~me men han in Essex , at Donmowe</l>
<l frag="III" benson="219" n="219">I gouerned hem so wel , after my lawe</l>
<l frag="III" benson="220" n="220">That iche of hem , ful blisful was and fawe</l>
<l frag="III" benson="221" n="221">To brynge me gay thynges , fro the feyre</l>
<l frag="III" benson="222" n="222">They were ful glad , whan I spak to he~ fayre</l>
<l frag="III" benson="223" n="223">For god it woot , I chidde hem spitously</l>
<l frag="III" benson="224" n="224">Now herkenetú how , I bar me ¸prely</l>
<l frag="III" benson="225" n="225">ñe wyse wyues , that can vnderstonde</l>
<l frag="III" benson="226" n="226">Thus shuld ©e speke , &#38; bere hem wrongö on honde</l>
<l frag="III" benson="227" n="227">For half so boldly , there can noman</l>
<l frag="III" benson="228" n="228">Sweren and lyen , as a womman can</l>
<l frag="III" benson="229" n="229">I sey nat this , be wyues that ben wyse</l><note><notetxt><ctp>229</ctp>There has been a pause in writing after this line. Sameshade of ink, although lighter.<resp>ODR</resp></notetxt></note>
<l frag="III" benson="230" n="230">But if it be , whan they he~ mys a vyse</l>
<l frag="III" benson="231" n="231">A wys wyf shal , if that she can hire good</l>
<l frag="III" benson="232" n="232">Bere hi~ an honde , that the kow is wood</l>
<l frag="III" benson="233" n="233"><emph>A</emph>nd take wytnesse , of hire owen mayde</l>
<l frag="III" benson="234" n="234">Of hire assent , but herkenetú how I sayde</l><note><notetxt><ctp>234</ctp>Cross in dry point in the left margin. Ink becomes darker too<resp>ODR</resp></notetxt></note>
<l frag="III" benson="235" n="235">Sire olde kaynard , is this thyn array</l>
<l frag="III" benson="236" n="236">Why is my neygúebores wyf , so gay</l>
<l frag="III" benson="237" n="237">She is honoured , ouä alle there she gotú</l>
<l frag="III" benson="238" n="238">I sitte at hom , I haue no thrifty clotú</l>
<l frag="III" benson="239" n="239">What dost thow , at my neyúebores hous</l>
<l frag="III" benson="240" n="240">Is she so fair , art thow so amerous</l>
<l frag="III" benson="241" n="241">What rovne ©e witú oure mayden , benedicite</l>
<l frag="III" benson="242" n="242">Sire olde lechour , late thyne iapes be</l>
<l frag="III" benson="243" n="243"><unr>xxxx</unr> if that I haue , a gosship~ or a freende</l><note><notetxt><ctp>243</ctp>tear in MS<resp>ODR</resp></notetxt></note> 
<l frag="III" benson="244" n="244"><unr>xxx</unr>ú outen gilt , ©e chiden as a fende</l><note><notetxt><ctp>244</ctp>tear in MS<resp>ODR</resp></notetxt></note> </folio>
