<?xml version="1.0" encoding="ISO-8859-1" ?><?xml-stylesheet type="text/xsl" href="../folio.xsl" ?><folio tale="wbp" n="68" side="v" label="68v" order="4" total="20">
<l frag="III" benson="113" n="113"><emph>I</emph> wol be stowe , the <emph>f</emph>lour of al myn age</l><note><notetxt><ctp>113</ctp>There is an abbreviation for a nota in the left margin in the top left corner just next to the line. It looks like the same ink, but different hand. Double check.<resp>ODR</resp></notetxt></note>
<l frag="III" benson="114" n="114">In the actes , and in the fruyt of mariage</l>
<l frag="III" benson="115" n="115">Telle me also , to what conclusione</l>
<l frag="III" benson="116" n="116">Were membres made , of generacione</l>
<l frag="III" benson="117" n="117">And of so ¹fyt wyse , a wygút I wrougút</l>
<l frag="III" benson="118" n="118">Trostetú rigút wel , they were nat made for nougút</l>
<l frag="III" benson="119" n="119">Glose who so wele , and sey bothe vp and doun</l>
<l frag="III" benson="120" n="120">That they weren I made , for purgacione</l>
<l frag="III" benson="121" n="121">Of vryne , and oure bothe thynges smale</l>
<l frag="III" benson="122" n="122">Weren eke to knowe , a femele fro a male</l>
<l frag="III" benson="123" n="123"><emph>A</emph>nd for noon other cause , sey ©e noo</l>
<l frag="III" benson="124" n="124">The ex¹ience wot wel , it is nat so</l>
<l frag="III" benson="125" n="125">So that the Clerkes , be nat witú me wrootú</l>
<l frag="III" benson="126" n="126">I seye this , that they maked be , for bothe</l>
<l frag="III" benson="127" n="127">This is to seyn , bothe for office &#38; for ease</l>
<l frag="III" benson="128" n="128">Of engendrure , there we nat god displeese</l>
<l frag="III" benson="129" n="129">Why shulde men ellis , in here bookes sette</l>
<l frag="III" benson="130" n="130">That man shal ©elde , to his wyf hire dette</l>
<l frag="III" benson="131" n="131">Now wher witú shuld he make , his paiement</l>
<l frag="III" benson="132" n="132">If that he ne vsed , his seely Instrument</l>
<l frag="III" benson="133" n="133">Than were they made , vp oon a creature</l>
<l frag="III" benson="134" n="134">To purge vryne , and eke for engendrure</l>
<l frag="III" benson="135" n="135">But I sey nougút , that euäy wygút is holde</l>
<l frag="III" benson="136" n="136">That hatú swicú harneys , as I to ©ow tolde</l>
<l frag="III" benson="137" n="137">To gon and vsen hem , in engendrure</l>
<l frag="III" benson="138" n="138">Than shulde men take , of chastitee no cure</l>
<l frag="III" benson="139" n="139">Crist was a mayde , and shapen as a man</l>
<l frag="III" benson="140" n="140">And many a Seynt , sithe æ  the world bygan</l>
<l frag="III" benson="141" n="141">ñet lyued they euäe , in ¹fyt chastitee</l>
<l frag="III" benson="142" n="142">I nyl envye , no virginitee</l>
<l frag="III" benson="143" n="143">Lat hem be breed , of pured whete seede</l>
<l frag="III" benson="144" n="144"><emph>A</emph>nd lat vs wyues , hote barly breede</l>
<l frag="III" benson="145" n="145">And ©et witú barly breed , Mark telle can</l>
<l frag="III" benson="146" n="146">Oure lord iúu , refresshed many a man</l>
<l frag="III" benson="147" n="147">In swicú estat , as god hatú cleped vs</l>
<l frag="III" benson="148" n="148">I wol ¹seuere , I nam nat precious</l>
<l frag="III" benson="149" n="149">In wyfhode wyl I vse , myn Instrument</l>
<l frag="III" benson="150" n="150">As freely as my makere , hatú it sent</l>
<l frag="III" benson="151" n="151">If I be daungerous , god ©eue me sorwe</l>
<l frag="III" benson="152" n="152">Myn husbonde shal it haue , bothe eue &#38; morwe</l>
<l frag="III" benson="153" n="153">Whan that hi~ liste , come fortú &#38; paie his dette</l>
<l frag="III" benson="154" n="154">An husbonde wol I haue , I wol nat lette</l>
<l frag="III" benson="155" n="155">Whicú shal be bothe , my dettour and my thral</l>
<l frag="III" benson="156" n="156">And haue his tribulacion , witú al</l></folio>
